flag/__init__.py
flag/py.typed
flag/data/LICENSE
flag/data/__init__.py
flag/data/region.xml
flag/data/subdivision.xml
emoji_country_flag-2.0.1.dist-info/LICENSE
emoji_country_flag-2.0.1.dist-info/METADATA
emoji_country_flag-2.0.1.dist-info/WHEEL
emoji_country_flag-2.0.1.dist-info/top_level.txt
emoji_country_flag-2.0.1.dist-info/zip-safe
emoji_country_flag-2.0.1.dist-info/RECORD
