Metadata-Version: 2.1
Name: emoji-country-flag
Version: 2.0.1
Summary: En/Decode unicode country flags emoji
Author-email: cuzi <cuzi@openmail.cc>
License: MIT
Project-URL: homepage, https://github.com/cvzi/flag
Project-URL: documentation, https://flag.readthedocs.io/
Project-URL: repository, https://github.com/cvzi/flag
Project-URL: downloads, https://pypi.org/project/emoji-country-flag/
Classifier: Development Status :: 5 - Production/Stable
Classifier: Programming Language :: Python
Classifier: Programming Language :: Python :: 3
Classifier: Programming Language :: Python :: 3.10
Classifier: Programming Language :: Python :: 3.11
Classifier: Programming Language :: Python :: 3.12
Classifier: Programming Language :: Python :: 3.13
Classifier: License :: OSI Approved :: MIT License
Classifier: Operating System :: OS Independent
Classifier: Topic :: Internet :: WWW/HTTP :: Dynamic Content
Classifier: Topic :: Communications :: Chat
Classifier: Topic :: Printing
Classifier: Topic :: Text Processing :: General
Classifier: Typing :: Typed
Requires-Python: >=3.10
License-File: LICENSE
Provides-Extra: coverage
Requires-Dist: coverage >=7.5.1 ; extra == 'coverage'
Requires-Dist: codacy-coverage >=1.3.11 ; extra == 'coverage'
Provides-Extra: docs
Requires-Dist: sphinx >=7.3.7 ; extra == 'docs'
Requires-Dist: sphinx-rtd-theme >=2.0.0 ; extra == 'docs'
Requires-Dist: sphinxcontrib-jquery >=4.1 ; extra == 'docs'
Provides-Extra: ruff
Requires-Dist: ruff >=0.4.7 ; extra == 'ruff'
Provides-Extra: test
Requires-Dist: pytest >=8.2.2 ; extra == 'test'
Requires-Dist: emoji >=2.12.1 ; extra == 'test'
Requires-Dist: tox >=4.15.0 ; extra == 'test'
